ada/__init__.py
ada/config.py
ada/warnings.py
ada/api/__init__.py
ada/api/animations.py
ada/api/boolean.py
ada/api/bounding_box.py
ada/api/computed_placement.py
ada/api/connections.py
ada/api/curves.py
ada/api/exceptions.py
ada/api/fasteners.py
ada/api/groups.py
ada/api/mass.py
ada/api/nodes.py
ada/api/presentation_layers.py
ada/api/transforms.py
ada/api/user.py
ada/api/beams/__init__.py
ada/api/beams/base_bm.py
ada/api/beams/beam_revolved.py
ada/api/beams/beam_swept.py
ada/api/beams/beam_tapered.py
ada/api/beams/geom_beams.py
ada/api/beams/helpers.py
ada/api/containers/__init__.py
ada/api/containers/base.py
ada/api/containers/beams.py
ada/api/containers/connections.py
ada/api/containers/materials.py
ada/api/containers/nodes.py
ada/api/containers/plates.py
ada/api/containers/sections.py
ada/api/piping/__init__.py
ada/api/piping/base_piping.py
ada/api/plates/__init__.py
ada/api/plates/base_pl.py
ada/api/primitives/__init__.py
ada/api/primitives/base.py
ada/api/primitives/bool_half_space.py
ada/api/primitives/box.py
ada/api/primitives/cone.py
ada/api/primitives/cylinder.py
ada/api/primitives/extruded_area_solid.py
ada/api/primitives/primitive_face.py
ada/api/primitives/revolved_area_solid.py
ada/api/primitives/sphere.py
ada/api/primitives/swept_area_solid.py
ada/api/spatial/__init__.py
ada/api/spatial/assembly.py
ada/api/spatial/equipment.py
ada/api/spatial/part.py
ada/api/walls/__init__.py
ada/api/walls/base_walls.py
ada/base/__init__.py
ada/base/adacpp_interface.py
ada/base/changes.py
ada/base/ifc_types.py
ada/base/physical_objects.py
ada/base/root.py
ada/base/types.py
ada/base/units.py
ada/cache/__init__.py
ada/cache/reader.py
ada/cache/store.py
ada/cache/utils.py
ada/cache/writer.py
ada/cadit/__init__.py
ada/cadit/e3d/__init__.py
ada/cadit/e3d/write_mac.py
ada/cadit/gxml/__init__.py
ada/cadit/gxml/sat_helpers.py
ada/cadit/gxml/store.py
ada/cadit/gxml/utils.py
ada/cadit/gxml/read/__init__.py
ada/cadit/gxml/read/helpers.py
ada/cadit/gxml/read/read_bcs.py
ada_py-0.7.8.dist-info/licenses/LICENSE
ada_py-0.7.8.dist-info/METADATA
ada_py-0.7.8.dist-info/WHEEL
ada_py-0.7.8.dist-info/entry_points.txt
ada_py-0.7.8.dist-info/top_level.txt
ada_py-0.7.8.dist-info/RECORD
