Metadata-Version: 2.4
Name: ada-py
Version: 0.7.8
Summary: Assembly for Design & Analysis - A python library for structural analysis and design
Author-email: "Kristoffer H. Andersen" <kristoffer_andersen@outlook.com>
License-Expression: GPL-3.0-or-later
Project-URL: Homepage, https://github.com/Krande/adapy
Project-URL: Bug Tracker, https://github.com/Krande/adapy/issues
Classifier: Development Status :: 3 - Alpha
Classifier: Intended Audience :: Science/Research
Classifier: Operating System :: OS Independent
Classifier: Programming Language :: Python
Classifier: Programming Language :: Python :: 3.10
Classifier: Programming Language :: Python :: 3.11
Classifier: Programming Language :: Python :: 3.12
Classifier: Topic :: Scientific/Engineering
Classifier: Topic :: Utilities
Requires-Python: >=3.10
License-File: LICENSE
Dynamic: license-file
